winkerberos-stubs/__init__.pyi
winkerberos_typed-0.5.0.dist-info/licenses/LICENSE.md
winkerberos_typed-0.5.0.dist-info/METADATA
winkerberos_typed-0.5.0.dist-info/WHEEL
winkerberos_typed-0.5.0.dist-info/top_level.txt
winkerberos_typed-0.5.0.dist-info/RECORD
