Metadata-Version: 2.4
Name: winkerberos-typed
Version: 0.5.0
Summary: Stubs file for winkerberos package
Author-email: DroidZed <41507665+DroidZed@users.noreply.github.com>
License-Expression: MIT
Project-URL: repository, https://github.com/DroidZed/winkerberos-typed
Project-URL: homepage, https://github.com/DroidZed/winkerberos-typed
Keywords: python3,windows,kerberos,authentication,spengo
Classifier: Intended Audience :: Developers
Classifier: Operating System :: Microsoft :: Windows
Classifier: Programming Language :: Python
Requires-Python: >=3.10
License-File: LICENSE.md
Dynamic: license-file
